cpplogger/__init__.py
cpplogger/cpplogger.py
cpplogger-0.0.2.dist-info/LICENSE
cpplogger-0.0.2.dist-info/METADATA
cpplogger-0.0.2.dist-info/WHEEL
cpplogger-0.0.2.dist-info/top_level.txt
cpplogger-0.0.2.dist-info/RECORD
